azure/security/__init__.py
azure_security_nspkg-1.0.0.dist-info/METADATA
azure_security_nspkg-1.0.0.dist-info/WHEEL
azure_security_nspkg-1.0.0.dist-info/top_level.txt
azure_security_nspkg-1.0.0.dist-info/RECORD
